plaid/__init__.py
plaid/cli.py
plaid/jinja_check.py
plaid/plaid.py
plaid/yml_check.py
plaid-0.1.7.dist-info/DESCRIPTION.rst
plaid-0.1.7.dist-info/METADATA
plaid-0.1.7.dist-info/RECORD
plaid-0.1.7.dist-info/WHEEL
plaid-0.1.7.dist-info/entry_points.txt
plaid-0.1.7.dist-info/metadata.json
plaid-0.1.7.dist-info/top_level.txt
