Metadata-Version: 1.1
Name: plaid
Version: 0.1.7
Summary: Python Ansible role checker
Home-page: https://github.com/sqrvrtx/plaid
Author: Scott Ison
Author-email: sqrvrtx@gmail.com
License: MIT license
Keywords: plaid
Platform: UNKNOWN
Classifier: Development Status :: 2 - Pre-Alpha
Classifier: Intended Audience :: Developers
Classifier: License :: OSI Approved :: MIT License
Classifier: Natural Language :: English
Classifier: Programming Language :: Python :: 2
Classifier: Programming Language :: Python :: 2.6
Classifier: Programming Language :: Python :: 2.7
